ogtk/._.DS_Store
ogtk/.gitignore
ogtk/UM.py
ogtk/__init__.py
ogtk/aln_to_mat.py
ogtk/demultiplex_readset_into_pickle.py
ogtk/fastball_headless_assembly.py
ogtk/fbli.py
ogtk/gegen.py
ogtk/kmers.py
ogtk/mp.py
ogtk/split_fastq.py
ogtk/ltr/__init__.py
ogtk/ltr/align.py
ogtk/ltr/bbin_alleles.py
ogtk/ltr/bin_alleles.py
ogtk/ltr/cluster.py
ogtk/ltr/compute_distance_headless.py
ogtk/ltr/ltr_matlin.py
ogtk/ltr/ltr_mtl.py
ogtk/ltr/ltr_run.py
ogtk/ltr/ltr_utils.py
ogtk/ltr/scmch_binalleles.py
ogtk/ltr/scsch_binalleles.py
ogtk/ltr/fracture/README.md
ogtk/ltr/fracture/__init__.py
ogtk/ltr/fracture/cli.py
ogtk/ltr/fracture/config.yml
ogtk/ltr/fracture/pipeline/README.md
ogtk/ltr/fracture/pipeline/__init__.py
ogtk/ltr/fracture/pipeline/api_ext.py
ogtk/ltr/fracture/pipeline/core.py
ogtk/ltr/fracture/pipeline/plot_gen.py
ogtk/ltr/fracture/pipeline/plotting.py
ogtk/ltr/fracture/pipeline/post.py
ogtk/ltr/fracture/pipeline/qc.py
ogtk/ltr/fracture/pipeline/steps.py
ogtk/ltr/fracture/pipeline/types.py
ogtk/ltr/shltr/__init__.py
ogtk/ltr/shltr/alg_emboss.py
ogtk/ltr/shltr/alg_lib.py
ogtk/ltr/shltr/bulk.py
ogtk/ltr/shltr/bulk_pipeline.py
ogtk/ltr/shltr/cluster.py
ogtk/ltr/shltr/ibars.py
ogtk/ltr/shltr/pipeline.py
ogtk/ltr/shltr/plot.py
ogtk/ltr/shltr/plot_bulk.py
ogtk/ltr/shltr/sc.py
ogtk/ltr/shltr/utils.py
ogtk/ngs/ssg.py
ogtk/utils/__init__.py
ogtk/utils/corr_dict.py
ogtk/utils/db.py
ogtk/utils/general.py
ogtk/utils/log.py
ogtk/utils/sc.py
ogtk/utils/sge.py
ogtk-0.1.8.dist-info/METADATA
ogtk-0.1.8.dist-info/WHEEL
ogtk-0.1.8.dist-info/licenses/LICENSE
ogtk-0.1.8.dist-info/RECORD
