Metadata-Version: 2.4
Name: ogtk
Version: 0.1.8
Summary: General tools for genomics and lineage tracing
Project-URL: Home-page, https://github.com/tzeitim/ogtk
Author: Pedro Olivares
Maintainer-email: Pedro Olivares <pedroy.final@gmail.com>
License-File: LICENSE
Classifier: License :: OSI Approved :: MIT License
Classifier: Operating System :: OS Independent
Classifier: Programming Language :: Python :: 3
Classifier: Programming Language :: Rust
Requires-Dist: colorhash
Requires-Dist: fastcluster
Requires-Dist: fastparquet
Requires-Dist: hdbscan
Requires-Dist: matplotlib
Requires-Dist: ngs-tools
Requires-Dist: numpy<2.0.0,>=1.21.0
Requires-Dist: pandas
Requires-Dist: polars
Requires-Dist: polars-hash
Requires-Dist: pyaml
Requires-Dist: pyarrow
Requires-Dist: pyfaidx
Requires-Dist: pyfasta
Requires-Dist: pysam
Requires-Dist: pyseq-align
Requires-Dist: regex
Requires-Dist: rich
Requires-Dist: scipy
Requires-Dist: seaborn
Requires-Dist: setuptools-rust
Requires-Dist: tables
Provides-Extra: doc
Requires-Dist: docutils!=0.18.*,!=0.19.*,>=0.8; extra == 'doc'
Requires-Dist: furo; extra == 'doc'
Requires-Dist: ipykernel; extra == 'doc'
Requires-Dist: ipython; extra == 'doc'
Requires-Dist: myst-nb; extra == 'doc'
Requires-Dist: myst-parser; extra == 'doc'
Requires-Dist: pandas; extra == 'doc'
Requires-Dist: sphinx-argparse; extra == 'doc'
Requires-Dist: sphinx-autobuild; extra == 'doc'
Requires-Dist: sphinx-autodoc-typehints; extra == 'doc'
Requires-Dist: sphinx-book-theme; extra == 'doc'
Requires-Dist: sphinx-book-theme>=1.0.0; extra == 'doc'
Requires-Dist: sphinx-copybutton; extra == 'doc'
Requires-Dist: sphinx-pyproject; extra == 'doc'
Requires-Dist: sphinx>=4; extra == 'doc'
Requires-Dist: sphinxcontrib-bibtex>=1.0.0; extra == 'doc'
Requires-Dist: sphinxext-opengraph; extra == 'doc'
Provides-Extra: rs
Requires-Dist: maturin; extra == 'rs'
Requires-Dist: patchelf; (sys_platform != 'darwin') and extra == 'rs'
Requires-Dist: rogtk; extra == 'rs'
Provides-Extra: sc
Requires-Dist: metacells; extra == 'sc'
Requires-Dist: scanpy; extra == 'sc'
